test.py
TDSpy/__init__.py
TDSpy/nld_spectrogram.py
TDSpy/sn_CrossCorrelation_and_TDS.py
TDSpy/sn_TDS.py
TDSpy/sn_feature_extraction.py
TDSpy/sn_getCrossCorrelation.py
TDSpy/sn_getStability.py
TDSpy/feature_extraction/sn_getBreathingRate.py
TDSpy/feature_extraction/sn_getEEGBandPower.py
TDSpy/feature_extraction/sn_getEventRate.py
TDSpy/feature_extraction/sn_getQRS.py
TDSpy/feature_extraction/sn_getVariance.py
TDSpy/signal_processing/nld_movingAverage.py
TDSpy/signal_processing/nld_movingMedian.py
TDSpy/signal_processing/sn_getExtrema.py
TDSpy/tools/csv_reader.py
TDSpy/tools/edf_reader.py
TDSpy/tools/get_SNR.py
TDSpy/tools/read_stages.py
TDSpy/tools/sn_plotGraph.py
TDSpy/tools/sn_plotTDS.py
TDSpy-1.0.1.dist-info/LICENSE
TDSpy-1.0.1.dist-info/METADATA
TDSpy-1.0.1.dist-info/WHEEL
TDSpy-1.0.1.dist-info/top_level.txt
TDSpy-1.0.1.dist-info/RECORD
