Metadata-Version: 2.1
Name: TDSpy
Version: 1.0.1
Summary: A small example package
Author: Sebastian Schmale
Author-email: "Tabea F. A. Steinbrinker" <tabea.steinbrinker@med.uni-goettingen.de>, "Dr. Nicolai Spicher" <nicolai.spicher@med.uni-goettingen.de>
Project-URL: Homepage, https://gitlab.gwdg.de/medinfpub/biosignal-processing-group/tdspy
Project-URL: Issues, https://gitlab.gwdg.de/medinfpub/biosignal-processing-group/tdspy/-/issues
Classifier: Programming Language :: Python :: 3
Classifier: License :: OSI Approved :: MIT License
Classifier: Operating System :: OS Independent
Requires-Python: >=3.8
License-File: LICENSE
